[
  {
    "name": "AI",
    "count": 2,
    "color": "pink",
    "img": "/images/tags/ai.jpg"
  },
  {
    "name": "Tech",
    "count": 1,
    "color": "blue",
    "img": "/images/tags/tech.jpg"
  },
  {
    "name": "OSS",
    "count": 1,
    "color": "pink",
    "img": "/images/tags/oss.jpg"
  },
  {
    "name": "Twitter",
    "count": 1,
    "color": "red",
    "img": "/images/tags/twitter.jpg"
  },
  {
    "name": "Projects",
    "count": 1,
    "color": "green",
    "img": "/images/tags/projects.jpg"
  },
  {
    "name": "TypeScript",
    "count": 1,
    "color": "blue",
    "img": "/images/tags/typescript.jpg"
  }
]